grvlmsnotes
